LICENSE.txt
MANIFEST.in
README.rst
bibulous.py
bibulous_authorextract.py
bibulous_profiler.py
bibulous_test.py
setup.py
bibulous.egg-info/PKG-INFO
bibulous.egg-info/SOURCES.txt
bibulous.egg-info/dependency_links.txt
bibulous.egg-info/top_level.txt
doc/Makefile
doc/banner.pdf
doc/banner.svg
doc/bibulous.rst
doc/bibulous_authorextract.rst
doc/bibulous_test.rst
doc/conf.py
doc/developer_guide.rst
doc/examples.rst
doc/faq.rst
doc/getting_started.rst
doc/guidelines_for_writing_style_templates.rst
doc/index.rst
doc/instructions_for_reporting_bugs.rst
doc/_build/doctrees/README.doctree
doc/_build/doctrees/bibulous.doctree
doc/_build/doctrees/bibulous_authorextract.doctree
doc/_build/doctrees/bibulous_test.doctree
doc/_build/doctrees/developer_guide.doctree
doc/_build/doctrees/examples.doctree
doc/_build/doctrees/faq.doctree
doc/_build/doctrees/getting_started.doctree
doc/_build/doctrees/guidelines_for_writing_style_templates.doctree
doc/_build/doctrees/index.doctree
doc/_build/doctrees/instructions_for_reporting_bugs.doctree
doc/_build/doctrees/modules.doctree
doc/_build/doctrees/mymodules.doctree
doc/_build/html/.buildinfo
doc/_build/html/bibulous.html
doc/_build/html/bibulous_authorextract.html
doc/_build/html/bibulous_test.html
doc/_build/html/developer_guide.html
doc/_build/html/examples.html
doc/_build/html/faq.html
doc/_build/html/genindex.html
doc/_build/html/getting_started.html
doc/_build/html/guidelines_for_writing_style_templates.html
doc/_build/html/index.html
doc/_build/html/instructions_for_reporting_bugs.html
doc/_build/html/np-modindex.html
doc/_build/html/objects.inv
doc/_build/html/py-modindex.html
doc/_build/html/search.html
doc/_build/html/searchindex.js
doc/_build/html/_images/example10.png
doc/_build/html/_images/example1a.png
doc/_build/html/_images/example1b.png
doc/_build/html/_images/example2a.png
doc/_build/html/_images/example2b.png
doc/_build/html/_images/example3.png
doc/_build/html/_images/example4.png
doc/_build/html/_images/example5a.png
doc/_build/html/_images/example5b.png
doc/_build/html/_images/example6.png
doc/_build/html/_images/example7.png
