Metadata-Version: 1.1
Name: bibulous
Version: 1.3.2
Summary: BibTeX replacement and enhancement
Home-page: https://github.com/nzhagen/bibulous
Author: Nathan Hagen
Author-email: and.the.light.shattered@gmail.com
License: MIT
Download-URL: https://github.com/nzhagen/bibulous/blob/master/bibulous.py
Keywords: bibtex,bibliography,parser,tex,latex
Platform: UNKNOWN
Classifier: Programming Language :: Python :: 2.7
Classifier: Development Status :: 4 - Beta
Classifier: License :: OSI Approved :: MIT License
Classifier: Operating System :: OS Independent
Classifier: Topic :: Text Processing :: Markup :: LaTeX
Classifier: Topic :: Text Processing
